tiffwrite-2025.12.0.dist-info/METADATA
tiffwrite-2025.12.0.dist-info/WHEEL
tiffwrite-2025.12.0.dist-info/licenses/LICENSE-APACHE
tiffwrite-2025.12.0.dist-info/licenses/LICENSE-MIT
tiffwrite/__init__.py
tiffwrite/tiffwrite_rs.abi3.so
tiffwrite-2025.12.0.dist-info/RECORD
