Metadata-Version: 2.4
Name: tiffwrite
Version: 2025.12.0
Classifier: License :: OSI Approved :: MIT License
Classifier: Programming Language :: Rust
Classifier: Programming Language :: Python
Classifier: Programming Language :: Python :: 3
Classifier: Programming Language :: Python :: 3 :: Only
Classifier: Programming Language :: Python :: 3.10
Classifier: Programming Language :: Python :: 3.11
Classifier: Programming Language :: Python :: 3.12
Classifier: Programming Language :: Python :: 3.13
Classifier: Programming Language :: Python :: 3.14
Requires-Dist: numpy
Requires-Dist: tqdm
Requires-Dist: pytest ; extra == 'test'
Requires-Dist: tifffile ; extra == 'test'
Requires-Dist: imagecodecs ; extra == 'test'
Provides-Extra: test
License-File: LICENSE-APACHE
License-File: LICENSE-MIT
Summary: Write BioFormats/ImageJ compatible tiffs with zstd compression in parallel.
Keywords: bioformats,tiff,ndarray,zstd,fiji
Home-Page: https://github.com/wimpomp/tiffwrite
Author-email: Wim Pomp <w.pomp@nki.nl>
License-Expression: MIT
Requires-Python: >=3.10
Project-URL: homepage, https://github.com/wimpomp/tiffwrite
Project-URL: repository, https://github.com/wimpomp/tiffwrite
